webgap/__init__.py
webgap-0.1.21.dist-info/LICENSE.txt
webgap-0.1.21.dist-info/METADATA
webgap-0.1.21.dist-info/WHEEL
webgap-0.1.21.dist-info/top_level.txt
webgap-0.1.21.dist-info/RECORD
